DBcm.py
dbcm-3.0.5.dist-info/METADATA
dbcm-3.0.5.dist-info/WHEEL
dbcm-3.0.5.dist-info/licenses/LICENCE
dbcm-3.0.5.dist-info/RECORD
