Metadata-Version: 2.3
Name: DBcm
Version: 3.0.5
Summary: Head First Python's Database Context Manager (updated for MariaDB)
Project-URL: Homepage, https://www.oreilly.com/library/view/head-first-python/9781492051282/
Project-URL: Github, https://github.com/headfirstpython/third
Author: Paul Barry (Head First Python)
Classifier: Development Status :: 5 - Production/Stable
Classifier: Intended Audience :: Developers
Classifier: License :: OSI Approved :: MIT License
Classifier: Operating System :: OS Independent
Classifier: Programming Language :: Python :: 3
Classifier: Topic :: Software Development :: Build Tools
Requires-Python: >=3.6
Requires-Dist: mariadb
